nikapis/__init__.py
nikapis/nikapis.py
nikapis-1.0.0.dist-info/METADATA
nikapis-1.0.0.dist-info/WHEEL
nikapis-1.0.0.dist-info/licenses/LICENSE
nikapis-1.0.0.dist-info/RECORD
