Metadata-Version: 2.3
Name: nikapis
Version: 1.0.0
Summary: A library with features that your bot and sites need, for example Crypto
Project-URL: Homepage, https://t.me/NikAPisChannel
Author-email: sina nik <nikpy.dev@gmail.com>
License-File: LICENSE
Classifier: License :: OSI Approved :: MIT License
Classifier: Operating System :: OS Independent
Classifier: Programming Language :: Python :: 3
Requires-Python: >=3.8
